[
  {
    "id": "WIR:536278466",
    "bucket": "Wiring Diagrams",
    "title": "ABS",
    "subtitle": "Late Production",
    "thumbnailHref": "api/source/MOTOR/graphic/11616076?w=240&h=220",
    "sort": 0
  },
  {
    "id": "WIR:536451103",
    "bucket": "Wiring Diagrams",
    "title": "ABS",
    "subtitle": "Early Production",
    "thumbnailHref": "api/source/MOTOR/graphic/11616238?w=240&h=220",
    "sort": 0
  },
  {
    "id": "WIR:536151625",
    "bucket": "Wiring Diagrams",
    "title": "Air Bags",
    "subtitle": "Early Production, UNDERHOOD",
    "thumbnailHref": "api/source/MOTOR/graphic/11616370?w=240&h=220",
    "sort": 0
  },
  {
    "id": "WIR:536233235",
    "bucket": "Wiring Diagrams",
    "title": "Air Bags",
    "subtitle": "Late Production, UNDERHOOD",
    "thumbnailHref": "api/source/MOTOR/graphic/11616233?w=240&h=220",
    "sort": 0
  },
  {
    "id": "WIR:536449798",
    "bucket": "Wiring Diagrams",
    "title": "Air Bags",
    "subtitle": "Late Production",
    "thumbnailHref": "api/source/MOTOR/graphic/11616232?w=240&h=220",
    "sort": 0
  },
  {
    "id": "WIR:536454533",
    "bucket": "Wiring Diagrams",
    "title": "Air Bags",
    "subtitle": "Early Production",
    "thumbnailHref": "api/source/MOTOR/graphic/11616369?w=240&h=220",
    "sort": 0
  },
  {
    "id": "WIR:536232586",
    "bucket": "Wiring Diagrams",
    "title": "Auxiliary Lamp",
    "subtitle": "Late Production",
    "thumbnailHref": "api/source/MOTOR/graphic/11616186?w=240&h=220",
    "sort": 0
  },
  {
    "id": "WIR:536233232",
    "bucket": "Wiring Diagrams",
    "title": "Battery",
    "subtitle": "Late Production",
    "thumbnailHref": "api/source/MOTOR/graphic/11616127?w=240&h=220",
    "sort": 0
  },
  {
    "id": "WIR:536076391",
    "bucket": "Wiring Diagrams",
    "title": "Charging System",
    "subtitle": "Late Production",
    "thumbnailHref": "api/source/MOTOR/graphic/11616162?w=240&h=220",
    "sort": 0
  },
  {
    "id": "WIR:536487453",
    "bucket": "Wiring Diagrams",
    "title": "Charging System",
    "subtitle": "Early Production",
    "thumbnailHref": "api/source/MOTOR/graphic/11616304?w=240&h=220",
    "sort": 0
  },
  {
    "id": "WIR:536203387",
    "bucket": "Wiring Diagrams",
    "title": "Communication Systems",
    "subtitle": "Late Production",
    "thumbnailHref": "api/source/MOTOR/graphic/11616194?w=240&h=220",
    "sort": 0
  },
  {
    "id": "WIR:536454531",
    "bucket": "Wiring Diagrams",
    "title": "Communication Systems",
    "subtitle": "Early Production",
    "thumbnailHref": "api/source/MOTOR/graphic/11616332?w=240&h=220",
    "sort": 0
  },
  {
    "id": "WIR:536246432",
    "bucket": "Wiring Diagrams",
    "title": "Computer Data Lines",
    "subtitle": "Late Production",
    "thumbnailHref": "api/source/MOTOR/graphic/11616198?w=240&h=220",
    "sort": 0
  },
  {
    "id": "WIR:536451106",
    "bucket": "Wiring Diagrams",
    "title": "Computer Data Lines",
    "subtitle": "Early Production",
    "thumbnailHref": "api/source/MOTOR/graphic/11616335?w=240&h=220",
    "sort": 0
  },
  {
    "id": "WIR:536895666",
    "bucket": "Wiring Diagrams",
    "title": "Computer Data Lines",
    "subtitle": "Late Production",
    "thumbnailHref": "api/source/MOTOR/graphic/11616189?w=240&h=220",
    "sort": 0
  },
  {
    "id": "WIR:537091502",
    "bucket": "Wiring Diagrams",
    "title": "Computer Data Lines",
    "subtitle": "Early Production",
    "thumbnailHref": "api/source/MOTOR/graphic/11616328?w=240&h=220",
    "sort": 0
  },
  {
    "id": "WIR:536584384",
    "bucket": "Wiring Diagrams",
    "title": "Cooling System",
    "subtitle": "Late Production",
    "thumbnailHref": "api/source/MOTOR/graphic/11616080?w=240&h=220",
    "sort": 0
  },
  {
    "id": "WIR:538082749",
    "bucket": "Wiring Diagrams",
    "title": "Cooling System",
    "subtitle": "Early Production",
    "thumbnailHref": "api/source/MOTOR/graphic/11616241?w=240&h=220",
    "sort": 0
  },
  {
    "id": "WIR:536246430",
    "bucket": "Wiring Diagrams",
    "title": "Courtesy Lamps",
    "subtitle": "Late Production",
    "thumbnailHref": "api/source/MOTOR/graphic/11616182?w=240&h=220",
    "sort": 0
  },
  {
    "id": "WIR:536300967",
    "bucket": "Wiring Diagrams",
    "title": "Courtesy Lamps",
    "subtitle": "Early Production",
    "thumbnailHref": "api/source/MOTOR/graphic/11616322?w=240&h=220",
    "sort": 0
  },
  {
    "id": "WIR:536451117",
    "bucket": "Wiring Diagrams",
    "title": "Daytime Running Lamps",
    "subtitle": "Late Production",
    "thumbnailHref": "api/source/MOTOR/graphic/11616177?w=240&h=220",
    "sort": 0
  },
  {
    "id": "WIR:537091508",
    "bucket": "Wiring Diagrams",
    "title": "Differential",
    "subtitle": "Late Production",
    "thumbnailHref": "api/source/MOTOR/graphic/11616074?w=240&h=220",
    "sort": 0
  },
  {
    "id": "WIR:536246421",
    "bucket": "Wiring Diagrams",
    "title": "Door Lamp",
    "subtitle": "Early Production",
    "thumbnailHref": "api/source/MOTOR/graphic/11616323?w=240&h=220",
    "sort": 0
  },
  {
    "id": "WIR:536300977",
    "bucket": "Wiring Diagrams",
    "title": "Door Lamp",
    "subtitle": "Late Production",
    "thumbnailHref": "api/source/MOTOR/graphic/11616183?w=240&h=220",
    "sort": 0
  },
  {
    "id": "WIR:536190493",
    "bucket": "Wiring Diagrams",
    "title": "Driver Information Center/Message Center",
    "subtitle": "Early Production, AUXILIARY AUDIO INPUT",
    "thumbnailHref": "api/source/MOTOR/graphic/11616311?w=240&h=220",
    "sort": 0
  },
  {
    "id": "WIR:536148406",
    "bucket": "Wiring Diagrams",
    "title": "Driver Information Center/Message Center",
    "subtitle": "Early Production, DIGITAL AUDIO SYSTEM",
    "thumbnailHref": "api/source/MOTOR/graphic/11616312?w=240&h=220",
    "sort": 0
  },
  {
    "id": "WIR:536246420",
    "bucket": "Wiring Diagrams",
    "title": "Driver Information Center/Message Center",
    "subtitle": "Early Production, EIGHT SPEAKERS",
    "thumbnailHref": "api/source/MOTOR/graphic/11616315?w=240&h=220",
    "sort": 0
  },
  {
    "id": "WIR:536487454",
    "bucket": "Wiring Diagrams",
    "title": "Driver Information Center/Message Center",
    "subtitle": "Early Production",
    "thumbnailHref": "api/source/MOTOR/graphic/11616309?w=240&h=220",
    "sort": 0
  },
  {
    "id": "WIR:536076392",
    "bucket": "Wiring Diagrams",
    "title": "Entertainment (Audio Systems)",
    "subtitle": "Late Production",
    "thumbnailHref": "api/source/MOTOR/graphic/11616168?w=240&h=220",
    "sort": 0
  },
  {
    "id": "WIR:536232584",
    "bucket": "Wiring Diagrams",
    "title": "Entertainment (Audio Systems)",
    "subtitle": "Late Production, WITH HIGH DEFINITION TUNER",
    "thumbnailHref": "api/source/MOTOR/graphic/11616172?w=240&h=220",
    "sort": 0
  },
  {
    "id": "WIR:536196336",
    "bucket": "Wiring Diagrams",
    "title": "Entertainment (Audio Systems)",
    "subtitle": "Early Production",
    "thumbnailHref": "api/source/MOTOR/graphic/11616313?w=240&h=220",
    "sort": 0
  },
  {
    "id": "WIR:536203383",
    "bucket": "Wiring Diagrams",
    "title": "Entertainment (Audio Systems)",
    "subtitle": "Late Production",
    "thumbnailHref": "api/source/MOTOR/graphic/11616170?w=240&h=220",
    "sort": 0
  },
  {
    "id": "WIR:537231558",
    "bucket": "Wiring Diagrams",
    "title": "Entertainment (Audio Systems)",
    "subtitle": "Late Production, WITH SATELLITE RADIO",
    "thumbnailHref": "api/source/MOTOR/graphic/11616171?w=240&h=220",
    "sort": 0
  },
  {
    "id": "WIR:536503135",
    "bucket": "Wiring Diagrams",
    "title": "Fog Lamps",
    "subtitle": "Late Production",
    "thumbnailHref": "api/source/MOTOR/graphic/11616181?w=240&h=220",
    "sort": 0
  },
  {
    "id": "WIR:536895652",
    "bucket": "Wiring Diagrams",
    "title": "Fog Lamps",
    "subtitle": "Early Production",
    "thumbnailHref": "api/source/MOTOR/graphic/11616318?w=240&h=220",
    "sort": 0
  },
  {
    "id": "WIR:536229329",
    "bucket": "Wiring Diagrams",
    "title": "Fuel Controls",
    "subtitle": "Early Production",
    "thumbnailHref": "api/source/MOTOR/graphic/11616259?w=240&h=220",
    "sort": 0
  },
  {
    "id": "WIR:537231554",
    "bucket": "Wiring Diagrams",
    "title": "Fuel Controls",
    "subtitle": "Late Production",
    "thumbnailHref": "api/source/MOTOR/graphic/11616089?w=240&h=220",
    "sort": 0
  },
  {
    "id": "WIR:536076395",
    "bucket": "Wiring Diagrams",
    "title": "Fuel Door Release",
    "subtitle": "Late Production",
    "thumbnailHref": "api/source/MOTOR/graphic/11616227?w=240&h=220",
    "sort": 0
  },
  {
    "id": "WIR:536151624",
    "bucket": "Wiring Diagrams",
    "title": "Fuel Door Release",
    "subtitle": "Early Production",
    "thumbnailHref": "api/source/MOTOR/graphic/11616361?w=240&h=220",
    "sort": 0
  },
  {
    "id": "WIR:536584386",
    "bucket": "Wiring Diagrams",
    "title": "Fuel Tank",
    "subtitle": "Late Production",
    "thumbnailHref": "api/source/MOTOR/graphic/11616106?w=240&h=220",
    "sort": 0
  },
  {
    "id": "WIR:536758390",
    "bucket": "Wiring Diagrams",
    "title": "Fuel Tank",
    "subtitle": "Early Production",
    "thumbnailHref": "api/source/MOTOR/graphic/11616262?w=240&h=220",
    "sort": 0
  },
  {
    "id": "WIR:536151622",
    "bucket": "Wiring Diagrams",
    "title": "Glove Compartment Lamp",
    "subtitle": "Early Production",
    "thumbnailHref": "api/source/MOTOR/graphic/11616345?w=240&h=220",
    "sort": 0
  },
  {
    "id": "WIR:536503711",
    "bucket": "Wiring Diagrams",
    "title": "Ground Distribution",
    "subtitle": "Late Production",
    "thumbnailHref": "api/source/MOTOR/graphic/11616160?w=240&h=220",
    "sort": 0
  },
  {
    "id": "WIR:538082750",
    "bucket": "Wiring Diagrams",
    "title": "Ground Distribution",
    "subtitle": "Early Production",
    "thumbnailHref": "api/source/MOTOR/graphic/11616303?w=240&h=220",
    "sort": 0
  },
  {
    "id": "WIR:536758391",
    "bucket": "Wiring Diagrams",
    "title": "Hazard Lamp",
    "subtitle": "Early Production",
    "thumbnailHref": "api/source/MOTOR/graphic/11616320?w=240&h=220",
    "sort": 0
  },
  {
    "id": "WIR:537091513",
    "bucket": "Wiring Diagrams",
    "title": "Hazard Lamp",
    "subtitle": "Late Production",
    "thumbnailHref": "api/source/MOTOR/graphic/11616179?w=240&h=220",
    "sort": 0
  },
  {
    "id": "WIR:536190506",
    "bucket": "Wiring Diagrams",
    "title": "Headlamps",
    "subtitle": "Late Production",
    "thumbnailHref": "api/source/MOTOR/graphic/11616174?w=240&h=220",
    "sort": 0
  },
  {
    "id": "WIR:536203373",
    "bucket": "Wiring Diagrams",
    "title": "Headlamps",
    "subtitle": "Early Production",
    "thumbnailHref": "api/source/MOTOR/graphic/11616317?w=240&h=220",
    "sort": 0
  },
  {
    "id": "WIR:536449793",
    "bucket": "Wiring Diagrams",
    "title": "Headlamps",
    "subtitle": "Late Production, WITH HIGH INTENSITY DISCHARGE",
    "thumbnailHref": "api/source/MOTOR/graphic/11616175?w=240&h=220",
    "sort": 0
  },
  {
    "id": "WIR:536203377",
    "bucket": "Wiring Diagrams",
    "title": "Heated Seats",
    "subtitle": "Early Production, CLIMATE CONTROL",
    "thumbnailHref": "api/source/MOTOR/graphic/11616352?w=240&h=220",
    "sort": 0
  },
  {
    "id": "WIR:536233234",
    "bucket": "Wiring Diagrams",
    "title": "Heated Seats",
    "subtitle": "Late Production, CLIMATE CONTROL",
    "thumbnailHref": "api/source/MOTOR/graphic/11616214?w=240&h=220",
    "sort": 0
  },
  {
    "id": "WIR:536487471",
    "bucket": "Wiring Diagrams",
    "title": "Heated Seats",
    "subtitle": "Late Production",
    "thumbnailHref": "api/source/MOTOR/graphic/11616209?w=240&h=220",
    "sort": 0
  },
  {
    "id": "WIR:536229330",
    "bucket": "Wiring Diagrams",
    "title": "Heated Windshield",
    "subtitle": "Early Production",
    "thumbnailHref": "api/source/MOTOR/graphic/11616269?w=240&h=220",
    "sort": 0
  },
  {
    "id": "WIR:536451115",
    "bucket": "Wiring Diagrams",
    "title": "Heated Windshield",
    "subtitle": "Late Production",
    "thumbnailHref": "api/source/MOTOR/graphic/11616115?w=240&h=220",
    "sort": 0
  },
  {
    "id": "WIR:536584387",
    "bucket": "Wiring Diagrams",
    "title": "HVAC Controls",
    "subtitle": "Late Production",
    "thumbnailHref": "api/source/MOTOR/graphic/11616113?w=240&h=220",
    "sort": 0
  },
  {
    "id": "WIR:536895651",
    "bucket": "Wiring Diagrams",
    "title": "HVAC Controls",
    "subtitle": "Early Production",
    "thumbnailHref": "api/source/MOTOR/graphic/11616267?w=240&h=220",
    "sort": 0
  },
  {
    "id": "WIR:536487470",
    "bucket": "Wiring Diagrams",
    "title": "Instrument Panel",
    "subtitle": "Late Production",
    "thumbnailHref": "api/source/MOTOR/graphic/11616205?w=240&h=220",
    "sort": 0
  },
  {
    "id": "WIR:536584380",
    "bucket": "Wiring Diagrams",
    "title": "Instrument Panel Lamps",
    "subtitle": "Early Production",
    "thumbnailHref": "api/source/MOTOR/graphic/11616325?w=240&h=220",
    "sort": 0
  },
  {
    "id": "WIR:536758396",
    "bucket": "Wiring Diagrams",
    "title": "Instrument Panel Lamps",
    "subtitle": "Late Production",
    "thumbnailHref": "api/source/MOTOR/graphic/11616185?w=240&h=220",
    "sort": 0
  },
  {
    "id": "WIR:536076386",
    "bucket": "Wiring Diagrams",
    "title": "Instrumentation",
    "subtitle": "Early Production",
    "thumbnailHref": "api/source/MOTOR/graphic/11616354?w=240&h=220",
    "sort": 0
  },
  {
    "id": "WIR:536233231",
    "bucket": "Wiring Diagrams",
    "title": "Instrumentation",
    "subtitle": "Late Production",
    "thumbnailHref": "api/source/MOTOR/graphic/11616119?w=240&h=220",
    "sort": 0
  },
  {
    "id": "WIR:536792738",
    "bucket": "Wiring Diagrams",
    "title": "Instrumentation",
    "subtitle": "Early Production",
    "thumbnailHref": "api/source/MOTOR/graphic/11616272?w=240&h=220",
    "sort": 0
  },
  {
    "id": "WIR:536246431",
    "bucket": "Wiring Diagrams",
    "title": "Interior Light Dimming",
    "subtitle": "Late Production",
    "thumbnailHref": "api/source/MOTOR/graphic/11616184?w=240&h=220",
    "sort": 0
  },
  {
    "id": "WIR:536503125",
    "bucket": "Wiring Diagrams",
    "title": "Interior Light Dimming",
    "subtitle": "Early Production",
    "thumbnailHref": "api/source/MOTOR/graphic/11616324?w=240&h=220",
    "sort": 0
  },
  {
    "id": "WIR:536096161",
    "bucket": "Wiring Diagrams",
    "title": "Junction Block",
    "subtitle": "Late Production, Front",
    "thumbnailHref": "api/source/MOTOR/graphic/11616129?w=240&h=220",
    "sort": 0
  },
  {
    "id": "WIR:536151628",
    "bucket": "Wiring Diagrams",
    "title": "Junction Block",
    "subtitle": "Late Production, CENTRALIZED",
    "thumbnailHref": "api/source/MOTOR/graphic/11616141?w=240&h=220",
    "sort": 0
  },
  {
    "id": "WIR:536229340",
    "bucket": "Wiring Diagrams",
    "title": "Junction Block",
    "subtitle": "Late Production, REAR",
    "thumbnailHref": "api/source/MOTOR/graphic/11616148?w=240&h=220",
    "sort": 0
  },
  {
    "id": "WIR:536503703",
    "bucket": "Wiring Diagrams",
    "title": "Keyless Entry",
    "subtitle": "Early Production",
    "thumbnailHref": "api/source/MOTOR/graphic/11616359?w=240&h=220",
    "sort": 0
  },
  {
    "id": "WIR:536758399",
    "bucket": "Wiring Diagrams",
    "title": "Keyless Entry",
    "subtitle": "Late Production, Front, REAR",
    "thumbnailHref": "api/source/MOTOR/graphic/11616223?w=240&h=220",
    "sort": 0
  },
  {
    "id": "WIR:538971206",
    "bucket": "Wiring Diagrams",
    "title": "Keyless Entry",
    "subtitle": "Late Production",
    "thumbnailHref": "api/source/MOTOR/graphic/11616220?w=240&h=220",
    "sort": 0
  },
  {
    "id": "WIR:536190496",
    "bucket": "Wiring Diagrams",
    "title": "Mobile Telephone",
    "subtitle": "Early Production",
    "thumbnailHref": "api/source/MOTOR/graphic/11616341?w=240&h=220",
    "sort": 0
  },
  {
    "id": "WIR:536190510",
    "bucket": "Wiring Diagrams",
    "title": "Mobile Telephone",
    "subtitle": "Late Production",
    "thumbnailHref": "api/source/MOTOR/graphic/11616204?w=240&h=220",
    "sort": 0
  },
  {
    "id": "WIR:536148424",
    "bucket": "Wiring Diagrams",
    "title": "Navigation System",
    "subtitle": "Late Production",
    "thumbnailHref": "api/source/MOTOR/graphic/11616203?w=240&h=220",
    "sort": 0
  },
  {
    "id": "WIR:536449784",
    "bucket": "Wiring Diagrams",
    "title": "Navigation System",
    "subtitle": "Early Production",
    "thumbnailHref": "api/source/MOTOR/graphic/11616340?w=240&h=220",
    "sort": 0
  },
  {
    "id": "WIR:536281248",
    "bucket": "Wiring Diagrams",
    "title": "Park Brake",
    "subtitle": "Early Production",
    "thumbnailHref": "api/source/MOTOR/graphic/11616237?w=240&h=220",
    "sort": 0
  },
  {
    "id": "WIR:536281259",
    "bucket": "Wiring Diagrams",
    "title": "Park Brake",
    "subtitle": "Late Production",
    "thumbnailHref": "api/source/MOTOR/graphic/11616075?w=240&h=220",
    "sort": 0
  },
  {
    "id": "WIR:536564862",
    "bucket": "Wiring Diagrams",
    "title": "Parking Aid",
    "subtitle": "Early Production",
    "thumbnailHref": "api/source/MOTOR/graphic/11616275?w=240&h=220",
    "sort": 0
  },
  {
    "id": "WIR:538085228",
    "bucket": "Wiring Diagrams",
    "title": "Parking Aid",
    "subtitle": "Late Production",
    "thumbnailHref": "api/source/MOTOR/graphic/11616122?w=240&h=220",
    "sort": 0
  },
  {
    "id": "WIR:536196335",
    "bucket": "Wiring Diagrams",
    "title": "Power Distribution",
    "subtitle": "Early Production",
    "thumbnailHref": "api/source/MOTOR/graphic/11616295?w=240&h=220",
    "sort": 0
  },
  {
    "id": "WIR:536093983",
    "bucket": "Wiring Diagrams",
    "title": "Power Locks",
    "subtitle": "Early Production, Front",
    "thumbnailHref": "api/source/MOTOR/graphic/11616362?w=240&h=220",
    "sort": 0
  },
  {
    "id": "WIR:536190499",
    "bucket": "Wiring Diagrams",
    "title": "Power Locks",
    "subtitle": "Early Production, REAR",
    "thumbnailHref": "api/source/MOTOR/graphic/11616363?w=240&h=220",
    "sort": 0
  },
  {
    "id": "WIR:536229335",
    "bucket": "Wiring Diagrams",
    "title": "Power Locks",
    "subtitle": "Early Production",
    "thumbnailHref": "api/source/MOTOR/graphic/11616360?w=240&h=220",
    "sort": 0
  },
  {
    "id": "WIR:536248353",
    "bucket": "Wiring Diagrams",
    "title": "Power Locks",
    "subtitle": "Late Production",
    "thumbnailHref": "api/source/MOTOR/graphic/11616226?w=240&h=220",
    "sort": 0
  },
  {
    "id": "WIR:536455239",
    "bucket": "Wiring Diagrams",
    "title": "Power Locks",
    "subtitle": "Late Production",
    "thumbnailHref": "api/source/MOTOR/graphic/11616221?w=240&h=220",
    "sort": 0
  },
  {
    "id": "WIR:536564877",
    "bucket": "Wiring Diagrams",
    "title": "Power Lumbar",
    "subtitle": "Late Production",
    "thumbnailHref": "api/source/MOTOR/graphic/11616216?w=240&h=220",
    "sort": 0
  },
  {
    "id": "WIR:536093981",
    "bucket": "Wiring Diagrams",
    "title": "Power Mirrors",
    "subtitle": "Early Production",
    "thumbnailHref": "api/source/MOTOR/graphic/11616344?w=240&h=220",
    "sort": 0
  },
  {
    "id": "WIR:536278473",
    "bucket": "Wiring Diagrams",
    "title": "Power Mirrors",
    "subtitle": "Late Production",
    "thumbnailHref": "api/source/MOTOR/graphic/11616208?w=240&h=220",
    "sort": 0
  },
  {
    "id": "WIR:538085232",
    "bucket": "Wiring Diagrams",
    "title": "Power Seat",
    "subtitle": "Late Production",
    "thumbnailHref": "api/source/MOTOR/graphic/11616213?w=240&h=220",
    "sort": 0
  },
  {
    "id": "WIR:537231546",
    "bucket": "Wiring Diagrams",
    "title": "Power Seat",
    "subtitle": "Early Production",
    "thumbnailHref": "api/source/MOTOR/graphic/11616349?w=240&h=220",
    "sort": 0
  },
  {
    "id": "WIR:536076385",
    "bucket": "Wiring Diagrams",
    "title": "Power Windows",
    "subtitle": "Early Production, Front",
    "thumbnailHref": "api/source/MOTOR/graphic/11616353?w=240&h=220",
    "sort": 0
  },
  {
    "id": "WIR:536793911",
    "bucket": "Wiring Diagrams",
    "title": "Power Windows",
    "subtitle": "Late Production",
    "thumbnailHref": "api/source/MOTOR/graphic/11616218?w=240&h=220",
    "sort": 0
  },
  {
    "id": "WIR:536229344",
    "bucket": "Wiring Diagrams",
    "title": "Power/Auxiliary Outlet",
    "subtitle": "Late Production",
    "thumbnailHref": "api/source/MOTOR/graphic/11616219?w=240&h=220",
    "sort": 0
  },
  {
    "id": "WIR:536232579",
    "bucket": "Wiring Diagrams",
    "title": "Reverse Lamps",
    "subtitle": "Early Production",
    "thumbnailHref": "api/source/MOTOR/graphic/11616319?w=240&h=220",
    "sort": 0
  },
  {
    "id": "WIR:536454541",
    "bucket": "Wiring Diagrams",
    "title": "Reverse Lamps",
    "subtitle": "Late Production",
    "thumbnailHref": "api/source/MOTOR/graphic/11616178?w=240&h=220",
    "sort": 0
  },
  {
    "id": "WIR:536451109",
    "bucket": "Wiring Diagrams",
    "title": "Seat Belts",
    "subtitle": "Early Production",
    "thumbnailHref": "api/source/MOTOR/graphic/11616367?w=240&h=220",
    "sort": 0
  },
  {
    "id": "WIR:538971208",
    "bucket": "Wiring Diagrams",
    "title": "Seat Belts",
    "subtitle": "Late Production",
    "thumbnailHref": "api/source/MOTOR/graphic/11616230?w=240&h=220",
    "sort": 0
  },
  {
    "id": "WIR:536233224",
    "bucket": "Wiring Diagrams",
    "title": "Security/Anti-Theft",
    "subtitle": "Early Production",
    "thumbnailHref": "api/source/MOTOR/graphic/11616339?w=240&h=220",
    "sort": 0
  },
  {
    "id": "WIR:536196346",
    "bucket": "Wiring Diagrams",
    "title": "Security/Anti-Theft",
    "subtitle": "Late Production",
    "thumbnailHref": "api/source/MOTOR/graphic/11616202?w=240&h=220",
    "sort": 0
  },
  {
    "id": "WIR:537091497",
    "bucket": "Wiring Diagrams",
    "title": "Shock Damping Control",
    "subtitle": "Early Production",
    "thumbnailHref": "api/source/MOTOR/graphic/11616236?w=240&h=220",
    "sort": 0
  },
  {
    "id": "WIR:536487463",
    "bucket": "Wiring Diagrams",
    "title": "Shock Damping Control",
    "subtitle": "Late Production",
    "thumbnailHref": "api/source/MOTOR/graphic/11616073?w=240&h=220",
    "sort": 0
  },
  {
    "id": "WIR:536196343",
    "bucket": "Wiring Diagrams",
    "title": "Side Marker Lamp",
    "subtitle": "Late Production",
    "thumbnailHref": "api/source/MOTOR/graphic/11616176?w=240&h=220",
    "sort": 0
  },
  {
    "id": "WIR:537231545",
    "bucket": "Wiring Diagrams",
    "title": "Side Marker Lamp",
    "subtitle": "Early Production",
    "thumbnailHref": "api/source/MOTOR/graphic/11616321?w=240&h=220",
    "sort": 0
  },
  {
    "id": "WIR:536151627",
    "bucket": "Wiring Diagrams",
    "title": "Speed Controls",
    "subtitle": "Late Production",
    "thumbnailHref": "api/source/MOTOR/graphic/11616109?w=240&h=220",
    "sort": 0
  },
  {
    "id": "WIR:536455220",
    "bucket": "Wiring Diagrams",
    "title": "Speed Controls",
    "subtitle": "Early Production",
    "thumbnailHref": "api/source/MOTOR/graphic/11616264?w=240&h=220",
    "sort": 0
  },
  {
    "id": "WIR:538971188",
    "bucket": "Wiring Diagrams",
    "title": "Starting",
    "subtitle": "Early Production",
    "thumbnailHref": "api/source/MOTOR/graphic/11616242?w=240&h=220",
    "sort": 0
  },
  {
    "id": "WIR:536758394",
    "bucket": "Wiring Diagrams",
    "title": "Starting",
    "subtitle": "Late Production",
    "thumbnailHref": "api/source/MOTOR/graphic/11616082?w=240&h=220",
    "sort": 0
  },
  {
    "id": "WIR:536233221",
    "bucket": "Wiring Diagrams",
    "title": "Steering Column",
    "subtitle": "Early Production",
    "thumbnailHref": "api/source/MOTOR/graphic/11616240?w=240&h=220",
    "sort": 0
  },
  {
    "id": "WIR:536246426",
    "bucket": "Wiring Diagrams",
    "title": "Steering Column",
    "subtitle": "Late Production",
    "thumbnailHref": "api/source/MOTOR/graphic/11616078?w=240&h=220",
    "sort": 0
  },
  {
    "id": "WIR:536233226",
    "bucket": "Wiring Diagrams",
    "title": "Sun Roof",
    "subtitle": "Early Production",
    "thumbnailHref": "api/source/MOTOR/graphic/11616366?w=240&h=220",
    "sort": 0
  },
  {
    "id": "WIR:536564879",
    "bucket": "Wiring Diagrams",
    "title": "Sun Roof",
    "subtitle": "Late Production",
    "thumbnailHref": "api/source/MOTOR/graphic/11616229?w=240&h=220",
    "sort": 0
  },
  {
    "id": "WIR:538971187",
    "bucket": "Wiring Diagrams",
    "title": "Symbol ID",
    "subtitle": "Early Production",
    "thumbnailHref": "api/source/MOTOR/graphic/11616234?w=240&h=220",
    "sort": 0
  },
  {
    "id": "WIR:536503130",
    "bucket": "Wiring Diagrams",
    "title": "Symbol ID",
    "subtitle": "Late Production",
    "thumbnailHref": "api/source/MOTOR/graphic/11616071?w=240&h=220",
    "sort": 0
  },
  {
    "id": "WIR:536278465",
    "bucket": "Wiring Diagrams",
    "title": "Tire Pressure Monitoring System",
    "subtitle": "Late Production",
    "thumbnailHref": "api/source/MOTOR/graphic/11616072?w=240&h=220",
    "sort": 0
  },
  {
    "id": "WIR:536346458",
    "bucket": "Wiring Diagrams",
    "title": "Tire Pressure Monitoring System",
    "subtitle": "Early Production",
    "thumbnailHref": "api/source/MOTOR/graphic/11616235?w=240&h=220",
    "sort": 0
  },
  {
    "id": "WIR:536076389",
    "bucket": "Wiring Diagrams",
    "title": "Transmission Controls",
    "subtitle": "Late Production",
    "thumbnailHref": "api/source/MOTOR/graphic/11616104?w=240&h=220",
    "sort": 0
  },
  {
    "id": "WIR:536248337",
    "bucket": "Wiring Diagrams",
    "title": "Transmission Controls",
    "subtitle": "Early Production",
    "thumbnailHref": "api/source/MOTOR/graphic/11616261?w=240&h=220",
    "sort": 0
  },
  {
    "id": "WIR:536454542",
    "bucket": "Wiring Diagrams",
    "title": "Turn Signal Lamp",
    "subtitle": "Late Production",
    "thumbnailHref": "api/source/MOTOR/graphic/11616180?w=240&h=220",
    "sort": 0
  },
  {
    "id": "WIR:536096163",
    "bucket": "Wiring Diagrams",
    "title": "Video System",
    "subtitle": "Late Production",
    "thumbnailHref": "api/source/MOTOR/graphic/11616173?w=240&h=220",
    "sort": 0
  },
  {
    "id": "WIR:536793912",
    "bucket": "Wiring Diagrams",
    "title": "Wiper/Washer",
    "subtitle": "Late Production",
    "thumbnailHref": "api/source/MOTOR/graphic/11616228?w=240&h=220",
    "sort": 0
  },
  {
    "id": "WIR:538085220",
    "bucket": "Wiring Diagrams",
    "title": "Wiper/Washer",
    "subtitle": "Early Production",
    "thumbnailHref": "api/source/MOTOR/graphic/11616365?w=240&h=220",
    "sort": 0
  }
]